pyproject.toml
playtour/__init__.py
playtour/ways.py
playtour.egg-info/PKG-INFO
playtour.egg-info/SOURCES.txt
playtour.egg-info/dependency_links.txt
playtour.egg-info/requires.txt
playtour.egg-info/top_level.txt