Metadata-Version: 2.1
Name: playtour
Version: 0.0.3
Summary: Loop page with playwright
Author-email: ken <block24block@gmail.com>
Project-URL: Homepage, https://github.com/turnon/playtour
Project-URL: Bug Tracker, https://github.com/turnon/playtour/issues
Classifier: Programming Language :: Python :: 3
Classifier: License :: OSI Approved :: MIT License
Classifier: Operating System :: OS Independent
Requires-Python: >=3.7
